HTTPServerPY/__init__.py
HTTPServerPY/__main__.py
HTTPServerPY/connection.py
HTTPServerPY/extension.py
HTTPServerPY/httpHandler.py
HTTPServerPY/main.py
httpserverpy-0.0.2.dist-info/METADATA
httpserverpy-0.0.2.dist-info/WHEEL
httpserverpy-0.0.2.dist-info/licenses/LICENSE
httpserverpy-0.0.2.dist-info/RECORD
