Metadata-Version: 2.1
Name: HTTPServerPY
Version: 0.0.2
Summary: HTTP Server Py
Project-URL: Homepage, https://github.com/mo-inkhan/HTTPServerPY
Project-URL: Bug Tracker, https://github.com/mo-inkhan/HTTPServerPY/issues
Project-URL: Source, https://github.com/mo-inkhan/HTTPServerPY
Author-email: Moin Khan <mo.inkhan@aol.com>
License-File: LICENSE
Keywords: client,hyperdb,in-memory
Classifier: License :: OSI Approved :: MIT License
Classifier: Operating System :: OS Independent
Classifier: Programming Language :: Python :: 3
Requires-Python: >=3.7
